README.md
setup.cfg
setup.py
hertz_scraper/Car.py
hertz_scraper/Scraper.py
hertz_scraper/__init__.py
hertz_scraper.egg-info/PKG-INFO
hertz_scraper.egg-info/SOURCES.txt
hertz_scraper.egg-info/dependency_links.txt
hertz_scraper.egg-info/not-zip-safe
hertz_scraper.egg-info/top_level.txt