Metadata-Version: 1.0
Name: hertz-scraper
Version: 0.0.2
Summary: Hertz Car Sales Scraper
Home-page: UNKNOWN
Author: UNKNOWN
Author-email: UNKNOWN
License: UNKNOWN
Platform: UNKNOWN
